[{"scientific_name":"Phago loricatus","primary":true,"kingdom":"ANIMALIA","phylum":"CHORDATA","class":"ACTINOPTERYGII","order":"CHARACIFORMES","family":"DISTICHODONTIDAE","genus":"Phago","species":"loricatus","authority":"G\u00fcnther, 1865","infra_name":null,"infra_rank":null,"infra_authority":null,"stock_name":null,"species_id":181846,"main_common_name":"African pike-characin (FB)","modified_year":2010,"category":"LC","criteria":null,"assessmentid":"7748751","trend_id":4,"biome_marine":false,"biome_freshwater":true,"biome_terrestrial":false,"taxonomicnotes":null,"rationale":"This species has a relatively wide distribution but also has widespread threats. It is currently assessed as Least Concern on account of its wide distribution and lack of information on any population decline at this time.","assessor":"Lal\u00e8y\u00e8, P., Moelants, T. & Olaosebikan, B.D.","evaluator":"Snoeks, J., Tweddle, D., Getahun, A., Lal\u00e8y\u00e8, P., Paugy, D., Zaiss, R., Fishar, M.R.A & Brooks, E."}]
