[{"scientific_name":"Hemibagrus nemurus","primary":true,"kingdom":"ANIMALIA","phylum":"CHORDATA","class":"ACTINOPTERYGII","order":"SILURIFORMES","family":"BAGRIDAE","genus":"Hemibagrus","species":"nemurus","authority":"(Valenciennes, 1840)","infra_name":null,"infra_rank":null,"infra_authority":null,"stock_name":null,"species_id":180954,"main_common_name":"Yellow Catfish","modified_year":2012,"category":"LC","criteria":null,"assessmentid":"1681839","trend_id":4,"biome_marine":false,"biome_freshwater":true,"biome_terrestrial":false,"taxonomicnotes":"The name&#160;<span style=\"font-style: italic;\">H. nemurus&#160;</span>has been used for fishes throughout Southeast Asia. It is now restricted to a species distributed only in Java, with populations in other parts of the Sundaic region (Malay Peninsula, Sumatra and Borneo) referring to a different species (H.H. Ng pers. comm. 2011), while the populations from the Mekong, Chao Phraya and Mae&#160;Khlong drainages are&#160;most likely&#160;<span style=\"font-style: italic;\">H. spilopterus</span>&#160;(Ng and Rainboth 1999; H.H. Ng pers. comm. 2011).","rationale":"The species appears to be still common in Java. It is found in rivers (polluted as some of them may be), and also known from impoundments. It is considered Least Concern at present, however there is a need for comprehensive surveys of Java's freshwater systems to ascertain the true status of its biodiversity.<span><span></span>","assessor":"Ng, H.H.","evaluator":"Kottelat, M. & Allen, D.J."}]
