{"identifier":401108,"scientificName":"Melanoides tuberculata","richness_score":72.4327,"synonyms":[{"synonym":"Alasmodonta zollingeri Mousson, 1849","relationship":"synonym"},{"synonym":"Ampullaria ampullacea Linnaeus, 1758","relationship":"synonym"},{"synonym":"Anisus leucostoma Millet, 1813","relationship":"synonym"},{"synonym":"Anisus spirorbis Linnaeus, 1758","relationship":"synonym"},{"synonym":"Anodonta beringiana Middendorff, 1851","relationship":"synonym"},{"synonym":"Anodonta cellensis Schr\u00f6ter, 1779","relationship":"synonym"},{"synonym":"Anodonta cyrea Drou\u00ebt, 1881","relationship":"synonym"},{"synonym":"Anodonta cyreum Drou\u00ebt, 1881","relationship":"synonym"},{"synonym":"Anodonta piscinalis Nilsson, 1823","relationship":"synonym"},{"synonym":"Anodonta trapezea von Ihering, 1890","relationship":"synonym"},{"synonym":"Assiminea philippinica O. Boettger, 1887","relationship":"synonym"},{"synonym":"Baicalia dybowkskiana Lindholm, 1909","relationship":"synonym"},{"synonym":"Baicalia elata W. Dybowski, 1875","relationship":"synonym"},{"synonym":"Baicalia florii W. Dybowski, 1875","relationship":"synonym"},{"synonym":"Baicalia godlewskii W. Dybowski, 1875","relationship":"synonym"},{"synonym":"Baicalia herderiana Lindholm, 1909","relationship":"synonym"},{"synonym":"Baicalia korotnewi Lindholm, 1909","relationship":"synonym"},{"synonym":"Baicalia nana Lindholm, 1909","relationship":"synonym"},{"synonym":"Baicalia oviformis W. Dybowski, 1875","relationship":"synonym"},{"synonym":"Baicalia pulchella W. Dybowski, 1875","relationship":"synonym"},{"synonym":"Baicalia pulla W. Dybowski, 1875","relationship":"synonym"},{"synonym":"Baicalia wrzeniowskii W. Dybowski, 1875","relationship":"synonym"},{"synonym":"Bathyomphalus contortus Linnaeus, 1758","relationship":"synonym"},{"synonym":"Bellamya javanica von Dem Busch, 1844","relationship":"synonym"},{"synonym":"Benedictia limnaeoides Shrenck, 1867","relationship":"synonym"},{"synonym":"Bithynia striatula Benson, 1842","relationship":"synonym"},{"synonym":"Canidia helena von dem Busch, 1847","relationship":"synonym"},{"synonym":"Cardium edule Linnaeus, 1758","relationship":"synonym"},{"synonym":"Chilina tehuelcha d\u2019Orbigny, 1838","relationship":"synonym"},{"synonym":"Choanomphalus amauronius Bourguignat, 1860","relationship":"synonym"},{"synonym":"Choanomphalus euristomus Lindholm, 1909","relationship":"synonym"},{"synonym":"Choanomphalus maacki Gerstfeldt, 1859","relationship":"synonym"},{"synonym":"Choanomphalus microtrochus Lindholm, 1909","relationship":"synonym"},{"synonym":"Clithon ualanensis von Martens in Weber, 1897","relationship":"synonym"},{"synonym":"Colletopterum ponderosum C. Pfeiffer, 1825","relationship":"synonym"},{"synonym":"Corbicula fluminea","relationship":"synonym"},{"synonym":"Corbicula fluminea M\u00fcller, 1774","relationship":"synonym"},{"synonym":"Dreissena polymorpha Pallas, 1771","relationship":"synonym"},{"synonym":"Fagotia acicularis A. Ferussac, 1823","relationship":"synonym"},{"synonym":"Fossaria truncatula M\u00fcller, 1774","relationship":"synonym"},{"synonym":"Gabbia orcula Frauenfeld, 1862","relationship":"synonym"},{"synonym":"Gangetia miliacea Nevill, 1880","relationship":"synonym"},{"synonym":"Glabaris trapesialis Lamarck, 1819","relationship":"synonym"},{"synonym":"Hydrobia k\u00fcsteri Strobel, 1874","relationship":"synonym"},{"synonym":"Incertihydrobia teesdalei Verdcourt, 1958","relationship":"synonym"},{"synonym":"Lanistes farleri Craven, 1880","relationship":"synonym"},{"synonym":"Limnaea javanica von Martens, 1881","relationship":"synonym"},{"synonym":"Limnaeus javanica von Martens, 1881","relationship":"synonym"},{"synonym":"Limnaeus javanicus von Martens, 1867","relationship":"synonym"},{"synonym":"Limnaeus longulus Mousson, 1848","relationship":"synonym"},{"synonym":"Limnaeus succineus Deshayes, 1834","relationship":"synonym"},{"synonym":"Lithoglyphus naticoides C. Pfeiffer, 1828","relationship":"synonym"},{"synonym":"Littoridina choapensis Biese, 1944","relationship":"synonym"},{"synonym":"Littoridina copiapoensis Biese, 1944","relationship":"synonym"},{"synonym":"Littoridina oblonga Biese, 1944","relationship":"synonym"},{"synonym":"Lymnaea auricularia Linnaeus, 1758","relationship":"synonym"},{"synonym":"Lymnaea lagotis Schrank, 1803","relationship":"synonym"},{"synonym":"Lymnaea ovata Draparnaud, 1805","relationship":"synonym"},{"synonym":"Lymnaea peregra M\u00fcller, 1774","relationship":"synonym"},{"synonym":"Lymnaea stagnalis Linnaeus, 1758","relationship":"synonym"},{"synonym":"Lymnaea truncatula M\u00fcller, 1774","relationship":"synonym"},{"synonym":"Margaritifera margaritifera Linnaeus, 1758","relationship":"synonym"},{"synonym":"Megalovalvata piligera Lindholm, 1909","relationship":"synonym"},{"synonym":"Melampus fasciatus Deshayes, 1830","relationship":"synonym"},{"synonym":"Melania amabilis Horst & Schepman, 1899","relationship":"synonym"},{"synonym":"Melania angularis von Martens, 1897","relationship":"synonym"},{"synonym":"Melania beryllina Brot, 1860","relationship":"synonym"},{"synonym":"Melania bifasciata Mousson, 1869","relationship":"synonym"},{"synonym":"Melania canalis Gassies, XXXX","relationship":"synonym"},{"synonym":"Melania coarctata Lamarck, XXXX","relationship":"synonym"},{"synonym":"Melania coarctata Philippi, 1847","relationship":"synonym"},{"synonym":"Melania crepidinata Reeve, 1859","relationship":"synonym"},{"synonym":"Melania cylindracea Tenison-Woods, XXXX","relationship":"synonym"},{"synonym":"Melania cylindrica Mousson, 1848","relationship":"synonym"},{"synonym":"Melania denisoniensis Brot, 1874","relationship":"synonym"},{"synonym":"Melania distinguenda Brot, 1874","relationship":"synonym"},{"synonym":"Melania dominula Tapparone-Canefri, 1883","relationship":"synonym"},{"synonym":"Melania exusta Reeve, 1859","relationship":"synonym"},{"synonym":"Melania fasciolata Olivier, 1804","relationship":"synonym"},{"synonym":"Melania formosensis E. A. Smith, 1878","relationship":"synonym"},{"synonym":"Melania inhonesta von dem Busch, 1847","relationship":"synonym"},{"synonym":"Melania javanica Brot, 1870","relationship":"synonym"},{"synonym":"Melania judaica Mousson, 1855","relationship":"synonym"},{"synonym":"Melania juncea Lea, 1850","relationship":"synonym"},{"synonym":"Melania junghuhni Schepman, 1896","relationship":"synonym"},{"synonym":"Melania juvenilis Lescke, XXXX","relationship":"synonym"},{"synonym":"Melania layardi Dohrn, 1858","relationship":"synonym"},{"synonym":"Melania mageni Gassies, XXXX","relationship":"synonym"},{"synonym":"Melania malayana Brot, 1874","relationship":"synonym"},{"synonym":"Melania mariei Gassies, XXXX","relationship":"synonym"},{"synonym":"Melania moesta Hinds, 1844","relationship":"synonym"},{"synonym":"Melania montrouzieri Gassies, XXXX","relationship":"synonym"},{"synonym":"Melania nicobarica Tapparone-Canefri, 1883","relationship":"synonym"},{"synonym":"Melania ningpoensis Suvatti, 1950","relationship":"synonym"},{"synonym":"Melania obliquigranosa E. A. Smith, 1878","relationship":"synonym"},{"synonym":"Melania onca A. Adams & Angas, 1864","relationship":"synonym"},{"synonym":"Melania ornata von dem Busch, 1842","relationship":"synonym"},{"synonym":"Melania parreyssii Brot, 1874","relationship":"synonym"},{"synonym":"Melania pellicens Tapparone-Canefri, 1883","relationship":"synonym"},{"synonym":"Melania petitti Tapparone-Canefri, 1883","relationship":"synonym"},{"synonym":"Melania punctata Poitiez & Michaud, 1838","relationship":"synonym"},{"synonym":"Melania punctulata Reeve, 1859","relationship":"synonym"},{"synonym":"Melania pyramis Benson, 1836","relationship":"synonym"},{"synonym":"Melania pyramis Horst & Schepman, 1899","relationship":"synonym"},{"synonym":"Melania pyramis Hutton, XXXX","relationship":"synonym"},{"synonym":"Melania rivularis Philippi, 1847","relationship":"synonym"},{"synonym":"Melania rossiteri Gassies, XXXX","relationship":"synonym"},{"synonym":"Melania rothiana Mousson, 1841","relationship":"synonym"},{"synonym":"Melania rubropunctata Tristram, 1865","relationship":"synonym"},{"synonym":"Melania rustica Mousson, 1857","relationship":"synonym"},{"synonym":"Melania scalariformis Tenison Woods, 1877","relationship":"synonym"},{"synonym":"Melania seminuda von Martens, 1897","relationship":"synonym"},{"synonym":"Melania sentaniensis Schepman, XXXX","relationship":"synonym"},{"synonym":"Melania setosa Swainson, 1824","relationship":"synonym"},{"synonym":"Melania similis Schepman, XXXX","relationship":"synonym"},{"synonym":"Melania singularis Tapparone-Canefri, 1877","relationship":"synonym"},{"synonym":"Melania societatis Horst & Schepman, 1899","relationship":"synonym"},{"synonym":"Melania striatissima Schepman, XXXX","relationship":"synonym"},{"synonym":"Melania sturalis Phillip, XXXX","relationship":"synonym"},{"synonym":"Melania suturalis Philippi, 1847","relationship":"synonym"},{"synonym":"Melania terebra Lesson, XXXX","relationship":"synonym"},{"synonym":"Melania testudinaria von dem Busch, 1842","relationship":"synonym"},{"synonym":"Melania tigrina Hutton, 1850","relationship":"synonym"},{"synonym":"Melania truncatula Lamarck, 1822","relationship":"synonym"},{"synonym":"Melania trunculata Lamarck, 1822","relationship":"synonym"},{"synonym":"Melania tuberculata M\u00fcller 1774","relationship":"valid"},{"synonym":"Melania tuberculata M\u00fcller 1774","relationship":"synonym"},{"synonym":"Melania turriculus Lea, 1850","relationship":"synonym"},{"synonym":"Melania unifasciata Mousson, 1848","relationship":"synonym"},{"synonym":"Melania virgatula F\u00e9russac, 1834","relationship":"synonym"},{"synonym":"Melania virgula Quoy & Gaimard, 1834","relationship":"synonym"},{"synonym":"Melania waigiensis Brot, 1874","relationship":"synonym"},{"synonym":"Melania wilkinsonii Tenison Woods, 1877","relationship":"synonym"},{"synonym":"Melania woodwardi Martin 1905","relationship":"synonym"},{"synonym":"Melanoides brenchleyi Baird, 1873","relationship":"synonym"},{"synonym":"Melanoides fasciolata Olivier, 1804","relationship":"synonym"},{"synonym":"Melanoides inhambanica von Martens, 1860","relationship":"synonym"},{"synonym":"Melanoides lutosa Gould, 1847","relationship":"synonym"},{"synonym":"Melanoides peddamunigalensis Ray & Raychowdhuri, 1969","relationship":"synonym"},{"synonym":"Melanoides persulcata Mousson, 1869","relationship":"synonym"},{"synonym":"Melanoides samoensis Reeve, 1859","relationship":"synonym"},{"synonym":"Melanoides sclateri Godwin-Austen, 1883","relationship":"synonym"},{"synonym":"Melanoides tuberculata (M\u00fcller, 1774)","relationship":"synonym"},{"synonym":"Melanoides tuberculata M\u00fcller, 1774","relationship":"synonym"},{"synonym":"Melanoides tuberculata O. F. M\u00fcller, 1774","relationship":"synonym"},{"synonym":"Melanoides tuberculatus M\u00fcller, 1774","relationship":"synonym"},{"synonym":"Melanoides turberculata","relationship":"misspelling"},{"synonym":"Melanoides zengana Morelet, 1860","relationship":"synonym"},{"synonym":"Monodacna edentula Pallas, 1771","relationship":"synonym"},{"synonym":"Mutela bourguignati Bourguignat, 1885","relationship":"synonym"},{"synonym":"Mycetopoda siliquosa Spix, 1827","relationship":"synonym"},{"synonym":"Mysorella costigera K\u00fcster, 1852","relationship":"synonym"},{"synonym":"Navicella porcellana Linnaeus, 1758","relationship":"synonym"},{"synonym":"Navicella suborbicularis Sowerby, 1825","relationship":"synonym"},{"synonym":"Nerita subpunctata R\u00e9cluz, 1844","relationship":"synonym"},{"synonym":"Nerita tuberculata (O. F. M\u00fcller, 1774)","relationship":"synonym"},{"synonym":"Nerita tuberculata M\u00c3\u00bcller, 1774","relationship":"synonym"},{"synonym":"Nerita tuberculata M\u00fcller, 1774","relationship":"synonym"},{"synonym":"Nerita tuberculatus O.F. Muller, 1774","relationship":"homotypic synonym"},{"synonym":"Neritina brevispina Lamarck, 1822","relationship":"synonym"},{"synonym":"Neritina porcatum Gould, 1847","relationship":"synonym"},{"synonym":"Neritina pulligera Linnaeus, 1767","relationship":"synonym"},{"synonym":"Omphalotropis bifilaris Mousson, 1865","relationship":"synonym"},{"synonym":"Omphalotropis biliratus Mousson, 1865","relationship":"synonym"},{"synonym":"Omphalotropis conoidea Mousson, 1869","relationship":"synonym"},{"synonym":"Paladilhiopsis bureschi Wagner, 1927","relationship":"synonym"},{"synonym":"Planorbis carinatus","relationship":"synonym"},{"synonym":"Planorbis carinatus O. F. M\u00fcller, 1774","relationship":"synonym"},{"synonym":"Planorbis planorbis Linnaeus, 1758","relationship":"synonym"},{"synonym":"Pomacea castelloi Sowerby, 1904","relationship":"synonym"},{"synonym":"Pomacea gigas Spix in Wagner, 1827","relationship":"synonym"},{"synonym":"Pomacea paludosa Say, 1829","relationship":"synonym"},{"synonym":"Potadoma liricincta Smith, 1888","relationship":"synonym"},{"synonym":"Pseudanodonta complanata Rossm\u00e4ssler, 1835","relationship":"synonym"},{"synonym":"Pseudodon peguensis Anthony, 1865","relationship":"synonym"},{"synonym":"Septaria porcellana Linnaeus, 1758","relationship":"synonym"},{"synonym":"Spathopsis trapezia von Martens, 1897","relationship":"synonym"},{"synonym":"Sphaerium scaldianum Normand, 1844","relationship":"synonym"},{"synonym":"Strombus costatus Schroeter, 1779","relationship":"synonym"},{"synonym":"Theodoxus danubialis C. Pfeiffer, 1828","relationship":"synonym"},{"synonym":"Thiara australis I. Lea & H. C. Lea, 1851","relationship":"synonym"},{"synonym":"Thiara scitula Gould, 1847","relationship":"synonym"},{"synonym":"Thiara tuberculata (Mueller, 1774)","relationship":""},{"synonym":"Thiara tuberculata (Mueller, 1774)","relationship":"synonym"},{"synonym":"Thiara tuberculata M\u00fcller, 1774","relationship":"synonym"},{"synonym":"Tricula horae Annandale & Rao, 1925","relationship":"synonym"},{"synonym":"Unio douglasiae Griffith & Pidgeon, 1833","relationship":"synonym"},{"synonym":"Unio mutatus Mousson, 1849","relationship":"synonym"},{"synonym":"Unio pictorum Linnaeus, 1758","relationship":"synonym"},{"synonym":"Unio productus Mousson, 1848","relationship":"synonym"},{"synonym":"Unio tumidus Philipsson 1788","relationship":"synonym"},{"synonym":"Valvata aliena Westerlund, 1877","relationship":"synonym"},{"synonym":"Valvata piscinalis O. F. M\u00fcller, 1774","relationship":"synonym"},{"synonym":"Valvata sibirica Middendorff, 1851","relationship":"synonym"},{"synonym":"Villorita cyprinoides Gray, 1825","relationship":"synonym"},{"synonym":"Viviparus viviparus Linnaeus, 1758","relationship":"synonym"}],"vernacularNames":[{"vernacularName":"Nadel-Kronenschnecke","language":"de","eol_preferred":true},{"vernacularName":"Malaiische Turmdeckelschnecke","language":"de"},{"vernacularName":"Malayische Turmdeckelschnecke","language":"de"},{"vernacularName":"red-rim melania","language":"en","eol_preferred":true},{"vernacularName":"Malaysian Trumpet Snail","language":"en"},{"vernacularName":"M\u00e9lanie tropicale","language":"fr","eol_preferred":true}],"references":["Seddon M. & Rowson B. (2013). MolluscaFW: World Checklist of Freshwater Mollusca (version 2011). In: Species 2000 & ITIS Catalogue of Life, 11th March 2013 (Roskov Y., Kunze T., Paglinawan L., Orrell T., Nicolson D., Culham A., Bailly N., Kirk P., Bourgoin T., Baillargeon G., Hernandez F., De Wever A., eds). Digital resource at www.catalogueoflife.org/col/. Species 2000: Reading, UK.","Turgeon, D. D., A. E. Bogan, E. V. Coan, W. K. Emerson, W. G. Lyons, W. Pratt, et al. 1988. Common and scientific names of aquatic invertebrates from the United States and Canada: mollusks. American Fisheries Society Special Publication 16. vii + 277","Turgeon, D. D., J. F. Quinn, Jr., A. E. Bogan, E. V. Coan, F. G. Hochberg, W. G. Lyons, et al. 1998. Common and scientific names of aquatic invertebrates from the United States and Canada: Mollusks, 2nd ed. American Fisheries Society Special Publication 26. 526"],"taxonConcepts":[{"identifier":51295970,"scientificName":"Melanoides tuberculata","nameAccordingTo":"NCBI Taxonomy","canonicalForm":"Melanoides tuberculata","sourceIdentfier":"55729","taxonRank":"Species"},{"identifier":49401640,"scientificName":"Melanoides (Melanoides) tuberculata (M\u00fcller 1774)","nameAccordingTo":"Paleobiology Database","canonicalForm":"Melanoides tuberculata","sourceIdentfier":"urn:paleodb:tn134789","taxonRank":"Species"},{"identifier":41631191,"scientificName":"Melanoides tuberculatus (Muller, 1774)","nameAccordingTo":"GBIF Nub Taxonomy","canonicalForm":"Melanoides tuberculatus","sourceIdentfier":"2300939","taxonRank":"Species"},{"identifier":41631192,"scientificName":"Melanoides tuberculata (O.F. M\u00fcller, 1774)","nameAccordingTo":"GBIF Nub Taxonomy","canonicalForm":"Melanoides tuberculata","sourceIdentfier":"4362965","taxonRank":"Species"},{"identifier":46246872,"scientificName":"Melanoides tuberculatus (Muller, 1774)","nameAccordingTo":"Integrated Taxonomic Information System (ITIS)","canonicalForm":"Melanoides tuberculatus","sourceIdentfier":"71533","taxonRank":"Species"},{"identifier":49163091,"scientificName":"Melanoides (Melanoides) tuberculata M\u00fcller 1774","nameAccordingTo":"Paleobiology Database","canonicalForm":"Melanoides tuberculata","sourceIdentfier":"urn:paleodb:tn134789","taxonRank":"Species"},{"identifier":33238181,"scientificName":"Melanoides tuberculata (O.F. M\u00fcller, 1774)","nameAccordingTo":"WORMS Species Information (Marine Species)","canonicalForm":"Melanoides tuberculata","sourceIdentfier":"225694"},{"identifier":28001481,"scientificName":"Melanoides tuberculata (O.F. M\u00fcller, 1774)","nameAccordingTo":"WORMS Species Information (Marine Species)","canonicalForm":"Melanoides tuberculata","sourceIdentfier":"225694"},{"identifier":52522866,"scientificName":"Melanoides tuberculata M\u00fcller, 1774","nameAccordingTo":"Species 2000 & ITIS Catalogue of Life: April 2013","canonicalForm":"Melanoides tuberculata","sourceIdentfier":"13010744","taxonRank":"Species"},{"identifier":55834509,"scientificName":"Melanoides tuberculatus (Muller, 1774)","nameAccordingTo":"Integrated Taxonomic Information System (ITIS)","canonicalForm":"Melanoides tuberculatus","sourceIdentfier":"71533","taxonRank":"Species"},{"identifier":58012907,"scientificName":"Melanoides tuberculatus (Muller, 1774)","nameAccordingTo":"Extant & Habitat resource","canonicalForm":"Melanoides tuberculatus","sourceIdentfier":"10603561","taxonRank":"Species"},{"identifier":58012911,"scientificName":"Melanoides tuberculata (O.F. M\u00fcller, 1774)","nameAccordingTo":"Extant & Habitat resource","canonicalForm":"Melanoides tuberculata","sourceIdentfier":"11253545","taxonRank":"Species"},{"identifier":59560149,"scientificName":"Melanoides (Melanoides) tuberculata (M\u00fcller 1774)","nameAccordingTo":"Paleobiology Database","canonicalForm":"Melanoides tuberculata","sourceIdentfier":"134788","taxonRank":"Species"}],"dataObjects":[{"identifier":"969b91ed5a1817430f3bdca5be021330","dataObjectVersionID":26324919,"dataType":"http://purl.org/dc/dcmitype/Text","dataSubtype":"","vettedStatus":"Trusted","dataRating":2.5,"subject":"http://rs.tdwg.org/ontology/voc/SPMInfoItems#Description","mimeType":"text/html","title":"Summary","language":"en","license":"http://creativecommons.org/licenses/by/3.0/","rightsHolder":"India Biodiversity Portal","source":"http://indiabiodiversity.org/species/show/237297","description":"\"One of the most common and cosmopolitan freshwater molluscs, <i>Melanoides tuberculatus</i> is found mostly in lentic habitats, but occasionally in lotic habitats, all over the world.\"","agents":[{"full_name":"\"Chitra Ravi, Content Facilitator, India Biodiversity Portal & EOL Rubenstein Fellow 2012.\"","homepage":"","role":null},{"full_name":"\"N.A. Aravind Madhyastha, Sandeep Sen and Ramya Badrinath, Ashoka Trust for Research in Ecology and the Environment (ATREE), Bangalore, India.\"","homepage":"","role":null},{"full_name":"\"N.A. Aravind Madhyastha and Ramya Badrinath, Content Compilers, ATREE, India.\"","homepage":"","role":null},{"full_name":"India Biodiversity Portal","homepage":"http://indiabiodiversity.org/","role":"provider"}],"references":[]},{"identifier":"46289eeeb8d3091dfaccf4005d275c43","dataObjectVersionID":26048908,"dataType":"http://purl.org/dc/dcmitype/Text","dataSubtype":"","vettedStatus":"Trusted","dataRating":2.5,"subject":"http://rs.tdwg.org/ontology/voc/SPMInfoItems#Distribution","mimeType":"text/html","title":"Endemic Distribution","language":"en","license":"http://creativecommons.org/licenses/by/3.0/","rightsHolder":"India Biodiversity Portal","source":"http://indiabiodiversity.org/species/show/237297","description":"Non-endemic","agents":[{"full_name":"\"Chitra Ravi, Content Facilitator, India Biodiversity Portal & EOL Rubenstein Fellow 2012.\"","homepage":"","role":null},{"full_name":"\"N.A. Aravind Madhyastha, Sandeep Sen and Ramya Badrinath, Ashoka Trust for Research in Ecology and the Environment (ATREE), Bangalore, India.\"","homepage":"","role":null},{"full_name":"\"N.A. Aravind Madhyastha and Ramya Badrinath, Content Compilers, ATREE, India.\"","homepage":"","role":null},{"full_name":"India Biodiversity Portal","homepage":"http://indiabiodiversity.org/","role":"provider"}],"references":[]},{"identifier":"40f880f0183413408ef9d93f51325586","dataObjectVersionID":26048901,"dataType":"http://purl.org/dc/dcmitype/Text","dataSubtype":"","vettedStatus":"Trusted","dataRating":2.5,"subject":"http://rs.tdwg.org/ontology/voc/SPMInfoItems#Size","mimeType":"text/html","title":"Size","language":"en","license":"http://creativecommons.org/licenses/by/3.0/","rightsHolder":"India Biodiversity Portal","source":"http://indiabiodiversity.org/species/show/237297","description":"Average shell length: 20\u201327 mm.  Some specimens may be up to 80 mm in length.","agents":[{"full_name":"\"Chitra Ravi, Content Facilitator, India Biodiversity Portal & EOL Rubenstein Fellow 2012.\"","homepage":"","role":null},{"full_name":"\"N.A. Aravind Madhyastha, Sandeep Sen and Ramya Badrinath, Ashoka Trust for Research in Ecology and the Environment (ATREE), Bangalore, India.\"","homepage":"","role":null},{"full_name":"\"N.A. Aravind Madhyastha and Ramya Badrinath, Content Compilers, ATREE, India.\"","homepage":"","role":null},{"full_name":"India Biodiversity Portal","homepage":"http://indiabiodiversity.org/","role":"provider"}],"references":[]},{"identifier":"383ce9b55bcc7d5954c501d13ad20d65","dataObjectVersionID":17335717,"dataType":"http://purl.org/dc/dcmitype/Text","dataSubtype":"","vettedStatus":"Trusted","dataRating":2.5,"subject":"http://rs.tdwg.org/ontology/voc/SPMInfoItems#Habitat","mimeType":"text/html","language":"en","license":"http://creativecommons.org/publicdomain/mark/1.0/","source":"http://www.iobis.org/mapper/?taxon_id=469322","description":"Depth range based on 2 specimens in 1 taxon.<br><br>Environmental ranges<br>&nbsp;&nbsp;Depth range (m): 0.25 - 2<br><br>Graphical representation<br><br>Depth range (m): 0.25 - 2 <img src='http://chart.apis.google.com/chart?cht=bvs&chs=350x150&chd=t:0.25|1.75&chxr=0,0,3&chds=0,3&chbh=50,20,15&chxt=y&chm=N,FF0000,-1,,12|N,000000,0,,12,,c|N,00000000,1,,12,,c|N,ffffff,2,,12,,c&chma=20&chf=&chco=ffffff,389ced&chxl='><br>&nbsp;<br>Note: this information has not been validated. Check this *<a target='obis_gallery' href='http://www.eol.org/content_partners/257'>note</a>*. Your feedback is most welcome.","agents":[{"full_name":"Ocean Biogeographic Information System","homepage":"http://www.iobis.org/","role":"provider"}],"references":[]},{"identifier":"b32d9d0e3ea5d068778795b553e97278","dataObjectVersionID":26048904,"dataType":"http://purl.org/dc/dcmitype/Text","dataSubtype":"","vettedStatus":"Trusted","dataRating":2.5,"subject":"http://rs.tdwg.org/ontology/voc/SPMInfoItems#TrophicStrategy","mimeType":"text/html","title":"Trophic Strategy","language":"en","license":"http://creativecommons.org/licenses/by/3.0/","rightsHolder":"India Biodiversity Portal","source":"http://indiabiodiversity.org/species/show/237297","description":"Feeds primarily on algae.","agents":[{"full_name":"\"Chitra Ravi, Content Facilitator, India Biodiversity Portal & EOL Rubenstein Fellow 2012.\"","homepage":"","role":null},{"full_name":"\"N.A. Aravind Madhyastha, Sandeep Sen and Ramya Badrinath, Ashoka Trust for Research in Ecology and the Environment (ATREE), Bangalore, India.\"","homepage":"","role":null},{"full_name":"\"N.A. Aravind Madhyastha and Ramya Badrinath, Content Compilers, ATREE, India.\"","homepage":"","role":null},{"full_name":"India Biodiversity Portal","homepage":"http://indiabiodiversity.org/","role":"provider"}],"references":[]},{"identifier":"b47d011df0a66f3e7fad6fdd56f27783","dataObjectVersionID":26048903,"dataType":"http://purl.org/dc/dcmitype/Text","dataSubtype":"","vettedStatus":"Trusted","dataRating":2.5,"subject":"http://rs.tdwg.org/ontology/voc/SPMInfoItems#Ecology","mimeType":"text/html","title":"Ecology","language":"en","license":"http://creativecommons.org/licenses/by/3.0/","rightsHolder":"India Biodiversity Portal","source":"http://indiabiodiversity.org/species/show/237297","description":"Nocturnal burrowing species.","agents":[{"full_name":"\"Chitra Ravi, Content Facilitator, India Biodiversity Portal & EOL Rubenstein Fellow 2012.\"","homepage":"","role":null},{"full_name":"\"N.A. Aravind Madhyastha, Sandeep Sen and Ramya Badrinath, Ashoka Trust for Research in Ecology and the Environment (ATREE), Bangalore, India.\"","homepage":"","role":null},{"full_name":"\"N.A. Aravind Madhyastha and Ramya Badrinath, Content Compilers, ATREE, India.\"","homepage":"","role":null},{"full_name":"India Biodiversity Portal","homepage":"http://indiabiodiversity.org/","role":"provider"}],"references":[]},{"identifier":"547c129ccc8add7f68a985bb518b8b40","dataObjectVersionID":26324920,"dataType":"http://purl.org/dc/dcmitype/Text","dataSubtype":"","vettedStatus":"Trusted","dataRating":2.5,"subject":"http://rs.tdwg.org/ontology/voc/SPMInfoItems#Reproduction","mimeType":"text/html","title":"Reproduction","language":"en","license":"http://creativecommons.org/licenses/by/3.0/","rightsHolder":"India Biodiversity Portal","source":"http://indiabiodiversity.org/species/show/237297","description":"\"These snails become capable of reproduction at sizes as small as 5-10 mm in length. Females parthenogenic and ovo-viviparous. Under favourable conditions, females transfer fertilised eggs to brood pouch for hatching. 1-64 embryos produced. Juveniles  1.2-2.2 mm in size at birth.\"","agents":[{"full_name":"\"Chitra Ravi, Content Facilitator, India Biodiversity Portal & EOL Rubenstein Fellow 2012.\"","homepage":"","role":null},{"full_name":"\"N.A. Aravind Madhyastha, Sandeep Sen and Ramya Badrinath, Ashoka Trust for Research in Ecology and the Environment (ATREE), Bangalore, India.\"","homepage":"","role":null},{"full_name":"\"N.A. Aravind Madhyastha and Ramya Badrinath, Content Compilers, ATREE, India.\"","homepage":"","role":null},{"full_name":"India Biodiversity Portal","homepage":"http://indiabiodiversity.org/","role":"provider"}],"references":[]},{"identifier":"d643964b0a513a2cadacb0952579d468","dataObjectVersionID":26048910,"dataType":"http://purl.org/dc/dcmitype/Text","dataSubtype":"","vettedStatus":"Trusted","dataRating":2.5,"subject":"http://rs.tdwg.org/ontology/voc/SPMInfoItems#Trends","mimeType":"text/html","title":"Trends","language":"en","license":"http://creativecommons.org/licenses/by/3.0/","rightsHolder":"India Biodiversity Portal","source":"http://indiabiodiversity.org/species/show/237297","description":"Unknown.","agents":[{"full_name":"\"Chitra Ravi, Content Facilitator, India Biodiversity Portal & EOL Rubenstein Fellow 2012.\"","homepage":"","role":null},{"full_name":"\"N.A. Aravind Madhyastha, Sandeep Sen and Ramya Badrinath, Ashoka Trust for Research in Ecology and the Environment (ATREE), Bangalore, India.\"","homepage":"","role":null},{"full_name":"\"N.A. Aravind Madhyastha and Ramya Badrinath, Content Compilers, ATREE, India.\"","homepage":"","role":null},{"full_name":"India Biodiversity Portal","homepage":"http://indiabiodiversity.org/","role":"provider"}],"references":[]},{"identifier":"0dba7ef9cc4d9783b2e1db58f9ec50b7","dataObjectVersionID":26048912,"dataType":"http://purl.org/dc/dcmitype/Text","dataSubtype":"","vettedStatus":"Trusted","dataRating":2.5,"subject":"http://rs.tdwg.org/ontology/voc/SPMInfoItems#Threats","mimeType":"text/html","title":"Threats","language":"en","license":"http://creativecommons.org/licenses/by/3.0/","rightsHolder":"India Biodiversity Portal","source":"http://indiabiodiversity.org/species/show/237297","description":"One potential threat is that by sedimentation in fresh water habitats by deforestion and agriculture. Impacts of this threat still to be determined.","agents":[{"full_name":"\"Chitra Ravi, Content Facilitator, India Biodiversity Portal & EOL Rubenstein Fellow 2012.\"","homepage":"","role":null},{"full_name":"\"N.A. Aravind Madhyastha, Sandeep Sen and Ramya Badrinath, Ashoka Trust for Research in Ecology and the Environment (ATREE), Bangalore, India.\"","homepage":"","role":null},{"full_name":"\"N.A. Aravind Madhyastha and Ramya Badrinath, Content Compilers, ATREE, India.\"","homepage":"","role":null},{"full_name":"India Biodiversity Portal","homepage":"http://indiabiodiversity.org/","role":"provider"}],"references":[]},{"identifier":"2fd33bd68257197c0d1b7f5b7cd94821","dataObjectVersionID":26048913,"dataType":"http://purl.org/dc/dcmitype/Text","dataSubtype":"","vettedStatus":"Trusted","dataRating":2.5,"subject":"http://rs.tdwg.org/ontology/voc/SPMInfoItems#Use","mimeType":"text/html","title":"Uses","language":"en","license":"http://creativecommons.org/licenses/by/3.0/","rightsHolder":"India Biodiversity Portal","source":"http://indiabiodiversity.org/species/show/237297","description":"Often seen in freshwater aquariums.","agents":[{"full_name":"\"Chitra Ravi, Content Facilitator, India Biodiversity Portal & EOL Rubenstein Fellow 2012.\"","homepage":"","role":null},{"full_name":"\"N.A. Aravind Madhyastha, Sandeep Sen and Ramya Badrinath, Ashoka Trust for Research in Ecology and the Environment (ATREE), Bangalore, India.\"","homepage":"","role":null},{"full_name":"\"N.A. Aravind Madhyastha and Ramya Badrinath, Content Compilers, ATREE, India.\"","homepage":"","role":null},{"full_name":"India Biodiversity Portal","homepage":"http://indiabiodiversity.org/","role":"provider"}],"references":[]},{"identifier":"d5bb6e120aaed798a819cdc43540dbdc","dataObjectVersionID":26786757,"dataType":"http://purl.org/dc/dcmitype/StillImage","dataSubtype":"","vettedStatus":"Trusted","dataRating":3.75,"mimeType":"image/jpeg","title":"File:Melanoides tuberculata 01.jpg","language":"en","license":"http://creativecommons.org/publicdomain/mark/1.0/","source":"http://commons.wikimedia.org/wiki/File:Melanoides_tuberculata_01.jpg","description":"<i>Melanoides tuberculatus</i>","mediaURL":"http://upload.wikimedia.org/wikipedia/commons/8/8c/Melanoides_tuberculata_01.jpg","eolMediaURL":"http://media.eol.org/content/2009/09/15/21/96575_orig.jpg","eolThumbnailURL":"http://media.eol.org/content/2009/09/15/21/96575_98_68.jpg","agents":[{"full_name":"Marisa_C","homepage":"","role":"photographer"},{"full_name":"Wikimedia Commons","homepage":"http://commons.wikimedia.org/","role":"provider"}],"references":[]},{"identifier":"4f645f21accf00710205c3183baa1fce","dataObjectVersionID":23365934,"dataType":"http://purl.org/dc/dcmitype/StillImage","dataSubtype":"","vettedStatus":"Trusted","dataRating":2.5,"mimeType":"image/jpeg","created":"2013-02-13T06:12:08Z","modified":"2013-02-13T06:12:40Z","license":"http://creativecommons.org/licenses/by-nc/3.0/","rights":"Copyright Todd Jackson, licensed under a Attribution-NonCommercial License license: http://creativecommons.org/licenses/by-nc/3.0/","rightsHolder":"Todd Jackson","source":"http://www.inaturalist.org/photos/251416","description":"Part of a collection taken for an outreach event with City of Austin Watershed Protection and Austin Youth River Watch.","mediaURL":"http://static.inaturalist.org/photos/251416/original.JPG?1360735952","eolMediaURL":"http://media.eol.org/content/2013/02/26/17/88380_orig.jpg","eolThumbnailURL":"http://media.eol.org/content/2013/02/26/17/88380_98_68.jpg","latitude":30.27367,"longitude":-97.844435,"agents":[{"full_name":"inaturalist","homepage":"","role":"publisher"},{"full_name":"Todd Jackson","homepage":"","role":"creator"},{"full_name":"iNaturalist.org","homepage":"http://www.inaturalist.org","role":"provider"}],"references":[]},{"identifier":"aae4b87ba8d6b1aea17a7757305cd6c2","dataObjectVersionID":32331522,"dataType":"http://purl.org/dc/dcmitype/StillImage","dataSubtype":"","vettedStatus":"Trusted","dataRating":2.5,"mimeType":"image/jpeg","created":"2015-01-31T17:44:13Z","modified":"2015-01-31T17:44:31Z","license":"http://creativecommons.org/licenses/by-nc/3.0/","rights":"Copyright lovetodnc, licensed under a Attribution-NonCommercial License license: http://creativecommons.org/licenses/by-nc/3.0/","rightsHolder":"lovetodnc","source":"http://www.inaturalist.org/photos/1520849","mediaURL":"http://static.inaturalist.org/photos/1520849/original.jpg?1422726268","eolMediaURL":"http://media.eol.org/content/2015/03/15/01/61260_orig.jpg","eolThumbnailURL":"http://media.eol.org/content/2015/03/15/01/61260_98_68.jpg","latitude":36.101423,"longitude":-115.021002,"agents":[{"full_name":"inaturalist","homepage":"","role":"publisher"},{"full_name":"lovetodnc","homepage":"","role":"creator"},{"full_name":"iNaturalist.org","homepage":"http://www.inaturalist.org","role":"provider"}],"references":[]},{"identifier":"f784e83f20e72fe931526fb0fee4c3c5","dataObjectVersionID":32331566,"dataType":"http://purl.org/dc/dcmitype/StillImage","dataSubtype":"","vettedStatus":"Trusted","dataRating":2.5,"mimeType":"image/jpeg","created":"2015-01-31T18:31:07Z","modified":"2015-01-31T18:31:11Z","license":"http://creativecommons.org/licenses/by-nc/3.0/","rights":"Copyright scalesmegan, licensed under a Attribution-NonCommercial License license: http://creativecommons.org/licenses/by-nc/3.0/","rightsHolder":"scalesmegan","source":"http://www.inaturalist.org/photos/1520986","mediaURL":"http://static.inaturalist.org/photos/1520986/original.jpg?1422729068","eolMediaURL":"http://media.eol.org/content/2015/03/15/01/12163_orig.jpg","eolThumbnailURL":"http://media.eol.org/content/2015/03/15/01/12163_98_68.jpg","latitude":36.101253,"longitude":-115.021026,"agents":[{"full_name":"inaturalist","homepage":"","role":"publisher"},{"full_name":"scalesmegan","homepage":"","role":"creator"},{"full_name":"iNaturalist.org","homepage":"http://www.inaturalist.org","role":"provider"}],"references":[]},{"identifier":"e4222ca07ee264382456d7122e2a256b","dataObjectVersionID":32331640,"dataType":"http://purl.org/dc/dcmitype/StillImage","dataSubtype":"","vettedStatus":"Trusted","dataRating":2.5,"mimeType":"image/jpeg","created":"2015-01-31T19:41:40Z","modified":"2015-01-31T19:41:48Z","license":"http://creativecommons.org/licenses/by-nc/3.0/","rights":"Copyright gianpaolo2003, licensed under a Attribution-NonCommercial License license: http://creativecommons.org/licenses/by-nc/3.0/","rightsHolder":"gianpaolo2003","source":"http://www.inaturalist.org/photos/1521329","mediaURL":"http://static.inaturalist.org/photos/1521329/original.jpg?1422733305","eolMediaURL":"http://media.eol.org/content/2015/03/15/01/37344_orig.jpg","eolThumbnailURL":"http://media.eol.org/content/2015/03/15/01/37344_98_68.jpg","latitude":36.1013361667,"longitude":-115.0210583333,"agents":[{"full_name":"inaturalist","homepage":"","role":"publisher"},{"full_name":"gianpaolo2003","homepage":"","role":"creator"},{"full_name":"iNaturalist.org","homepage":"http://www.inaturalist.org","role":"provider"}],"references":[]},{"identifier":"dc454a71312872afa2f3679ef428f264","dataObjectVersionID":32331658,"dataType":"http://purl.org/dc/dcmitype/StillImage","dataSubtype":"","vettedStatus":"Trusted","dataRating":2.5,"mimeType":"image/jpeg","created":"2015-01-31T19:47:40Z","modified":"2015-01-31T19:47:46Z","license":"http://creativecommons.org/licenses/by-nc/3.0/","rights":"Copyright iicollin456, licensed under a Attribution-NonCommercial License license: http://creativecommons.org/licenses/by-nc/3.0/","rightsHolder":"iicollin456","source":"http://www.inaturalist.org/photos/1521404","mediaURL":"http://static.inaturalist.org/photos/1521404/original.jpg?1422733664","eolMediaURL":"http://media.eol.org/content/2015/03/15/01/54658_orig.jpg","eolThumbnailURL":"http://media.eol.org/content/2015/03/15/01/54658_98_68.jpg","latitude":36.10137,"longitude":-115.021079,"agents":[{"full_name":"inaturalist","homepage":"","role":"publisher"},{"full_name":"iicollin456","homepage":"","role":"creator"},{"full_name":"iNaturalist.org","homepage":"http://www.inaturalist.org","role":"provider"}],"references":[]},{"identifier":"831942c8b504d70c356ee48e2c25bdd1","dataObjectVersionID":32331678,"dataType":"http://purl.org/dc/dcmitype/StillImage","dataSubtype":"","vettedStatus":"Trusted","dataRating":2.5,"mimeType":"image/jpeg","created":"2015-01-31T20:10:55Z","modified":"2015-01-31T20:11:01Z","license":"http://creativecommons.org/licenses/by-nc/3.0/","rights":"Copyright Jim Boone, licensed under a Attribution-NonCommercial License license: http://creativecommons.org/licenses/by-nc/3.0/","rightsHolder":"Jim Boone","source":"http://www.inaturalist.org/photos/1521469","mediaURL":"http://static.inaturalist.org/photos/1521469/original.jpg?1422735057","eolMediaURL":"http://media.eol.org/content/2015/03/15/01/34721_orig.jpg","eolThumbnailURL":"http://media.eol.org/content/2015/03/15/01/34721_98_68.jpg","latitude":36.100228,"longitude":-115.021918,"agents":[{"full_name":"inaturalist","homepage":"","role":"publisher"},{"full_name":"Jim Boone","homepage":"","role":"creator"},{"full_name":"iNaturalist.org","homepage":"http://www.inaturalist.org","role":"provider"}],"references":[]},{"identifier":"f40d1d5e02c14735b223b33be126d2bd","dataObjectVersionID":32331681,"dataType":"http://purl.org/dc/dcmitype/StillImage","dataSubtype":"","vettedStatus":"Trusted","dataRating":2.5,"mimeType":"application/octet-stream","created":"2015-01-31T20:11:01Z","modified":"2015-01-31T20:11:10Z","license":"http://creativecommons.org/licenses/by-nc/3.0/","rights":"Copyright Jason Eckberg, licensed under a Attribution-NonCommercial License license: http://creativecommons.org/licenses/by-nc/3.0/","rightsHolder":"Jason Eckberg","source":"http://www.inaturalist.org/photos/1521473","mediaURL":"http://static.inaturalist.org/photos/1521473/original.jpg?1422735063","eolMediaURL":"http://media.eol.org/content/2015/03/15/01/39400_orig.jpg","eolThumbnailURL":"http://media.eol.org/content/2015/03/15/01/39400_98_68.jpg","latitude":36.10635094,"longitude":-115.0237787,"agents":[{"full_name":"inaturalist","homepage":"","role":"publisher"},{"full_name":"Jason Eckberg","homepage":"","role":"creator"},{"full_name":"iNaturalist.org","homepage":"http://www.inaturalist.org","role":"provider"}],"references":[]},{"identifier":"c0a7ba2dcaab7fd43f8b5cefea5d0fc3","dataObjectVersionID":32331847,"dataType":"http://purl.org/dc/dcmitype/StillImage","dataSubtype":"","vettedStatus":"Trusted","dataRating":2.5,"mimeType":"image/jpeg","created":"2015-01-31T23:15:51Z","modified":"2015-01-31T23:16:18Z","license":"http://creativecommons.org/licenses/by-nc/3.0/","rights":"Copyright gs323, licensed under a Attribution-NonCommercial License license: http://creativecommons.org/licenses/by-nc/3.0/","rightsHolder":"gs323","source":"http://www.inaturalist.org/photos/1522003","mediaURL":"http://static.inaturalist.org/photos/1522003/original.JPG?1422746175","eolMediaURL":"http://media.eol.org/content/2015/03/15/01/21265_orig.jpg","eolThumbnailURL":"http://media.eol.org/content/2015/03/15/01/21265_98_68.jpg","latitude":36.106225,"longitude":-115.023701,"agents":[{"full_name":"inaturalist","homepage":"","role":"publisher"},{"full_name":"gs323","homepage":"","role":"creator"},{"full_name":"iNaturalist.org","homepage":"http://www.inaturalist.org","role":"provider"}],"references":[]},{"identifier":"3d90de2ba535bec12fe7aeccf26e2c58","dataObjectVersionID":32277668,"dataType":"http://purl.org/dc/dcmitype/StillImage","dataSubtype":"","vettedStatus":"Trusted","dataRating":2.5,"mimeType":"image/jpeg","created":"2014-11-09T02:59:30Z","modified":"2014-11-09T02:59:48Z","license":"http://creativecommons.org/licenses/by-nc/3.0/","rights":"Copyright Damon Tighe, licensed under a Attribution-NonCommercial License license: http://creativecommons.org/licenses/by-nc/3.0/","rightsHolder":"Damon Tighe","source":"http://www.inaturalist.org/photos/1333530","mediaURL":"http://static.inaturalist.org/photos/1333530/original.jpg?1415501979","eolMediaURL":"http://media.eol.org/content/2015/03/12/20/77546_orig.jpg","eolThumbnailURL":"http://media.eol.org/content/2015/03/12/20/77546_98_68.jpg","latitude":33.42345,"longitude":-112.0713805,"agents":[{"full_name":"inaturalist","homepage":"","role":"publisher"},{"full_name":"Damon Tighe","homepage":"","role":"creator"},{"full_name":"iNaturalist.org","homepage":"http://www.inaturalist.org","role":"provider"}],"references":[]},{"identifier":"731551e62881dd49be0edd0f576c89cc","dataObjectVersionID":21320216,"dataType":"http://purl.org/dc/dcmitype/StillImage","dataSubtype":"Map","vettedStatus":"Trusted","dataRating":2.5,"mimeType":"image/jpeg","title":"Discover Life: Point Map of Melanoides tuberculata","language":"en","license":"http://creativecommons.org/licenses/by-nc-sa/3.0/","rightsHolder":"Discover Life and original sources","source":"http://www.discoverlife.org/mp/20q?search=Melanoides+tuberculata","description":"<br>Please see details, credits, terms of use and the latest version of the map at <a href='http://www.discoverlife.org/20/m?kind=Melanoides+tuberculata&b=EOL/pages/401108'>Discover Life</a>.<br>Explore <a href='http://www.discoverlife.org/mp/20q?search=Melanoides+tuberculata&b=EOL/pages/401108'><i>Melanoides tuberculata</i></a> in Discover Life.","mediaURL":"http://www.discoverlife.org/mp/20m?map=Melanoides+tuberculata","eolMediaURL":"http://media.eol.org/content/2012/07/24/09/20319_orig.jpg","eolThumbnailURL":"http://media.eol.org/content/2012/07/24/09/20319_98_68.jpg","agents":[{"full_name":"John Pickering","homepage":"http://www.discoverlife.org/","role":"compiler"},{"full_name":"Discover Life","homepage":"http://www.discoverlife.org/","role":"provider"}],"references":[]},{"identifier":"a1ff9086de4241c21720b8b207f3ffc5","dataObjectVersionID":21320217,"dataType":"http://purl.org/dc/dcmitype/StillImage","dataSubtype":"Map","vettedStatus":"Trusted","dataRating":2.5,"mimeType":"image/jpeg","title":"Discover Life: Point Map of Melanoides tuberculatus","language":"en","license":"http://creativecommons.org/licenses/by-nc-sa/3.0/","rightsHolder":"Discover Life and original sources","source":"http://www.discoverlife.org/mp/20q?search=Melanoides+tuberculatus","description":"<br>Please see details, credits, terms of use and the latest version of the map at <a href='http://www.discoverlife.org/20/m?kind=Melanoides+tuberculatus&b=EOL/pages/401108'>Discover Life</a>.<br>Explore <a href='http://www.discoverlife.org/mp/20q?search=Melanoides+tuberculatus&b=EOL/pages/401108'><i>Melanoides tuberculatus</i></a> in Discover Life.","mediaURL":"http://www.discoverlife.org/mp/20m?map=Melanoides+tuberculatus","eolMediaURL":"http://media.eol.org/content/2012/01/17/18/90405_orig.jpg","eolThumbnailURL":"http://media.eol.org/content/2012/01/17/18/90405_98_68.jpg","agents":[{"full_name":"John Pickering","homepage":"http://www.discoverlife.org/","role":"compiler"},{"full_name":"Discover Life","homepage":"http://www.discoverlife.org/","role":"provider"}],"references":[]}]}
