[{"scientific_name":"Devario acrostomus","primary":true,"kingdom":"ANIMALIA","phylum":"CHORDATA","class":"ACTINOPTERYGII","order":"CYPRINIFORMES","family":"CYPRINIDAE","genus":"Devario","species":"acrostomus","authority":"(Fang &amp; Kottelat, 1999)","infra_name":null,"infra_rank":null,"infra_authority":null,"stock_name":null,"species_id":180900,"main_common_name":null,"modified_year":2012,"category":"DD","criteria":null,"assessmentid":"1675529","trend_id":4,"biome_marine":false,"biome_freshwater":true,"biome_terrestrial":false,"taxonomicnotes":"This species was described from the Nam Mang drainage, which forms part of the Mekong River drainage in northern Lao PDR (Fang and Kottelat 1999). It was originally described as <em>Danio acrostomus</em>, but was transferred to the genus <em>Devario</em> by Fang (2003).","rationale":"There is insufficient information about the geographic distribution and population size of this species for an accurate assessment and it is assessed as Data Deficient. The genus <span style=\"font-style: italic;\">Devario </span>can be found in highly disturbed habitats.","assessor":"Ng, H.H.","evaluator":"Kullander, S.O. & Allen, D.J."}]
