[{"scientific_name":"Puntius ticto","primary":true,"kingdom":"ANIMALIA","phylum":"CHORDATA","class":"ACTINOPTERYGII","order":"CYPRINIFORMES","family":"CYPRINIDAE","genus":"Puntius","species":"ticto","authority":"(Hamilton, 1822)","infra_name":null,"infra_rank":null,"infra_authority":null,"stock_name":null,"species_id":166621,"main_common_name":"Ticto barb","modified_year":2010,"category":"LC","criteria":null,"assessmentid":"6249085","trend_id":4,"biome_marine":false,"biome_freshwater":true,"biome_terrestrial":false,"taxonomicnotes":"There are no taxonomic issues regarding this species.","rationale":"<p><span style=\"font-style: italic;\">Puntius ticto</span> is a very common and widespread species with no known major widespread threats.   It is therefore assessed as Least Concern.   &#160;&#160;&#160;&#160; </p>","assessor":"Dahanukar, N.","evaluator":"Juffe Bignoli, D., Rema Devi, K.R., Chaudhry, S. & Dey, S.C."}]
